{
  "shard_id": "S2A_NATURAL_08",
  "stage": "S2A_NATURAL",
  "cells_done": {
    "S2A_NATURAL_c0044": {
      "wall_s": 2718.29,
      "n_rows": 150
    },
    "S2A_NATURAL_c0045": {
      "wall_s": 2672.48,
      "n_rows": 150
    },
    "S2A_NATURAL_c0046": {
      "wall_s": 1884.73,
      "n_rows": 30
    },
    "S2A_NATURAL_c0047": {
      "wall_s": 1877.74,
      "n_rows": 30
    },
    "S2A_NATURAL_c0048": {
      "wall_s": 1872.0,
      "n_rows": 30
    },
    "S2A_NATURAL_c0049": {
      "wall_s": 1871.82,
      "n_rows": 30
    }
  },
  "fieldnames": [
    "cell_id",
    "shard_id",
    "side",
    "pattern",
    "rho_bar",
    "nu",
    "M",
    "seed",
    "image",
    "arm",
    "PSNR",
    "SSIM",
    "LPIPS",
    "rad_nrmse",
    "flux_dev",
    "lam_tv",
    "mean_counts",
    "optical_time_s",
    "dark_frac",
    "tau_err",
    "runtime_s",
    "select_runtime_s",
    "PSNR_rad",
    "C_hat",
    "S_N2",
    "V0_exact",
    "muprime0_exact",
    "omega_A",
    "c_used",
    "sigma_grad_arm",
    "lambda_tv_arm",
    "audit_status",
    "d_ratio",
    "q_d",
    "q_mean",
    "leak_suspect"
  ],
  "wall_accum_s": 12897.17,
  "aborted_over_budget": false,
  "wall_s": 12897.17,
  "process_cpu_s": 12895.45
}